Metadata-Version: 1.1
Name: xoc-utils-python
Version: 0.0.2
Summary: An XO core utils project.
Home-page: https://github.com/newellxo/xoc-utils-python
Author: XO Core Dev Team
Author-email: UNKNOWN
License: UNKNOWN
Keywords: xoc-utils-python kafka client utils
Platform: UNKNOWN
Classifier: Development Status :: 3 - Alpha
Classifier: Intended Audience :: Developers
Classifier: Topic :: Software Development :: Build Tools
Classifier: License :: OSI Approved :: MIT License
Classifier: Programming Language :: Python :: 3.6
